{
  "dataList": [
    {
      "id": "1",
      "content": "Проверьте, какие ЭГО вы выдали своим грешникам, и какие ресурсы они потребляют, чтобы сформировать максимально эффективную в бою команду."
    },
    {
      "id": "2",
      "content": "ЭГО могут изменить ход боя в вашу пользу, если сила духа ваших грешников достаточно высока."
    },
    {
      "id": "3",
      "content": "Когда противник падает духом и впадает в состояние срыва, он получает негативные эффекты, предоставляющие вам преимущество."
    },
    {
      "id": "4",
      "content": "Если здоровье оглушённого персонажа пересекают следующий порог оглушения, он получает дополнительный урон."
    }
  ]
}