{
  "list": [
    {
      "id": 10701,
      "isBatonPassOn": true,
      "stageLevel": 46,
      "stageType": "Abnormality",
      "participantInfo": {
        "min": 6,
        "max": 6
      },
      "waveList": [
        {
          "battleMapInfo": {
            "mapName": "Cp7_BloodfiendWar"
          },
          "unitList": [
            {
              "unitID": 8393,
              "unitCount": 2,
              "unitLevel": 46
            },
            {
              "unitID": 8392,
              "unitCount": 2,
              "unitLevel": 46
            }
          ],
          "bgmList": [
            "Battle_Cp7_Ally_1",
            "Battle_Cp7_Enemy_1"
          ],
          "enemyPositionID": 93
        },
        {
          "battleMapInfo": {
            "mapName": "Cp7_FathomsOfLamancha_1"
          },
          "unitList": [
            {
              "unitID": 8373,
              "unitCount": 2,
              "unitLevel": 46
            },
            {
              "unitID": 8374,
              "unitCount": 2,
              "unitLevel": 46
            }
          ],
          "enemyPositionID": 93
        }
      ],
      "staminaCost": 0,
      "recommendedLevel": 46,
      "turnLimit": 99,
      "questlist": [
        {
          "args": [
            "10"
          ],
          "localizeId": 1
        }
      ],
      "rewardList": [],
      "story": {
        "enter": [
          "7D102B"
        ],
        "exit": [
          "7D102A"
        ]
      },
      "stageScriptList": [
        "Chapter7SetAllyDefaultMp", "400001"
      ],
      "abstainSupporterCharacterIds": [ 3 ]
    },
    {
      "id": 10702,
      "isBatonPassOn": true,
      "stageLevel": 48,
      "stageType": "Abnormality",
      "participantInfo": {
        "min": 6,
        "max": 6
      },
      "waveList": [
        {
          "battleMapInfo": {
            "mapName": "Cp7_FathomsOfLamancha_1"
          },
          "unitList": [
            {
              "unitID": 8379,
              "unitCount": 1,
              "unitLevel": 48
            }
          ],
          "bgmList": [
            "Battle_Cp7_Ally_2",
            "Battle_Cp7_Enemy_2"
          ],
          "enemyPositionID": 13
        }
      ],
      "staminaCost": 0,
      "recommendedLevel": 48,
      "turnLimit": 99,
      "questlist": [
        {
          "args": [
            "10"
          ],
          "localizeId": 1
        }
      ],
      "stageScriptList": ["AbnormalityEvent", "Chapter7SetAllyDefaultMp"],
      "eventScriptName": "8379",
      "abnormalityEventList": [
        837901,
        837902
      ],
      "rewardList": [
        {
          "type": "EGO_GIFT",
          "rewardId": 9008,
          "num": 1,
          "prob": 1
        }
      ],
      "story": {
        "exit": [
          "7D103A"
        ]
      },
      "abstainSupporterCharacterIds": [ 3 ]
    },
    {
      "id": 10703,
      "isBatonPassOn": true,
      "stageLevel": 49,
      "stageType": "Abnormality",
      "participantInfo": {
        "min": 6,
        "max": 6
      },
      "battleCameraInfo": {
        "defaultPosX": 0,
        "defaultPosY": 0,
        "defaultPosZ": 20
      },
      "waveList": [
        {
          "battleMapInfo": {
            "mapName": "Cp7_FathomsOfLamancha_2"
          },
          "unitList": [
            {
              "unitID": 8376,
              "unitCount": 1,
              "unitLevel": 49
            }
          ],
          "bgmList": [
            "Battle_Cp7_Enemy_3"
          ],
          "enemyPositionID": 99,
          "allyPositionID": 102,
          "subUnitList": [
            {
              "unitID": 8377,
              "unitCount": 1,
              "unitLevel": 49,
              "isHide": true
            }
          ]
        }
      ],
      "staminaCost": 0,
      "recommendedLevel": 49,
      "turnLimit": 99,
      "questlist": [
        {
          "args": [
            "10"
          ],
          "localizeId": 1
        }
      ],
      "stageScriptList": ["8376", "Chapter7SetAllyDefaultMp"],
      "eventScriptName": "8376",
      "abnormalityEventList": [
        837601
      ],
      "rewardList": [
        {
          "type": "EGO_GIFT",
          "rewardId": 9047,
          "num": 1,
          "prob": 1
        }
      ],
      "abstainSupporterCharacterIds": [ 3 ]
    },
    {
      "id": 10706,
      "isBatonPassOn": true,
      "stageLevel": 50,
      "stageType": "Abnormality",
      "participantInfo": {
        "min": 6,
        "max": 6
      },
      "waveList": [
        {
          "battleMapInfo": {
            "mapName": "Cp7_FathomsOfLamancha_3"
          },
          "unitList": [
            {
              "unitID": 8375,
              "unitCount": 1,
              "unitLevel": 50
            },
            {
              "unitID": 8394,
              "unitCount": 1,
              "unitLevel": 50
            }
          ],
          "bgmList": [
            "Battle_Cp7_Enemy_4"
          ],
          "enemyPositionID": 19
        }
      ],
      "staminaCost": 0,
      "recommendedLevel": 50,
      "turnLimit": 99,
      "questlist": [
        {
          "args": [
            "10"
          ],
          "localizeId": 1
        }
      ],
      "rewardList": [
        {
          "type": "EGO_GIFT",
          "rewardId": 9036,
          "num": 1,
          "prob": 1
        }
      ],
      "story": {
        "enter": [
          "7D107B"
        ]
      },
      "stageScriptList": [
        "Chapter7SetAllyDefaultMp"
      ],
      "abstainSupporterCharacterIds": [ 3 ]
    },
    {
      "id": 10708,
      "isBatonPassOn": true,
      "stageLevel": 50,
      "stageType": "Abnormality",
      "participantInfo": {
        "min": 6,
        "max": 6
      },
      "waveList": [
        {
          "battleMapInfo": {
            "mapName": "Cp7_MiddleBosses",
            "mapSize": 34.0
          },
          "unitList": [
            {
              "unitID": 8378,
              "unitCount": 1,
              "unitLevel": 70
            },
            {
              "unitID": 8395,
              "unitCount": 1,
              "unitLevel": 70
            },
            {
              "unitID": 8396,
              "unitCount": 1,
              "unitLevel": 85
            }
          ],
          "bgmList": [
            "Battle_Cp7_Boss_5"
          ],
          "enemyPositionID": 100
        }
      ],
      "staminaCost": 0,
      "recommendedLevel": 50,
      "turnLimit": 99,
      "questlist": [
        {
          "args": [
            "10"
          ],
          "localizeId": 1
        }
      ],
      "rewardList": [
        {
          "type": "EGO_GIFT",
          "rewardId": 2056,
          "num": 1,
          "prob": 1
        }
      ],
      "story": {
        "enter": [
          "7D110B"
        ]
      },
      "stageScriptList": [
        "8378", "Chapter7SetAllyDefaultMp"
      ],
      "abstainSupporterCharacterIds": [ 3 ]
    },
    {
      "id": 10709,
      "isBatonPassOn": true,
      "stageLevel": 50,
      "stageType": "Abnormality",
      "participantInfo": {
        "min": 6,
        "max": 6
      },
      "waveList": [
        {
          "battleMapInfo": {
            "mapName": "Cp7_MiddleBosses"
          },
          "unitList": [
            {
              "unitID": 8380,
              "unitCount": 1,
              "unitLevel": 85
            }
          ],
          "bgmList": [
            "Battle_Cp7_Boss_3"
          ],
          "enemyPositionID": 86
        }
      ],
      "staminaCost": 0,
      "recommendedLevel": 50,
      "turnLimit": 99,
      "questlist": [
        {
          "args": [
            "10"
          ],
          "localizeId": 1
        }
      ],
      "rewardList": [
        {
          "type": "EGO_GIFT",
          "rewardId": 2047,
          "num": 1,
          "prob": 1
        },
        {
          "type": "EGO_GIFT",
          "rewardId": 2057,
          "num": 1,
          "prob": 1
        }
      ],
      "story": {
        "enter": [
          "7D111B"
        ],
        "exit": [
          "7D111A"
        ],
        "others": [
          {
            "phase": "AFTER_ROUND_END",
            "storyIndex": 0,
            "storyID": "7D111I"
          },
          {
            "phase": "AFTER_ROUND_END",
            "storyIndex": 1,
            "storyID": "7D111I2"
          },
          {
            "phase": "AFTER_ROUND_END",
            "storyIndex": 2,
            "storyID": "7D111I3"
          }
        ]
      },
      "stageScriptList": ["8380Story", "Chapter7SetAllyDefaultMpNotCustomizePosition"],
      "abstainSupporterCharacterIds": [ 3 ]
    },
    {
      "id": 10710,
      "stageLevel": 50,
      "isBatonPassOn": true,
      "stageType": "Abnormality",
      "participantInfo": {
        "min": 6,
        "max": 6
      },
      "battleCameraInfo": {
        "defaultPosX": 0,
        "defaultPosY": 0,
        "defaultPosZ": 20
      },
      "waveList": [
        {
          "battleMapInfo": {
            "mapName": "Cp7_BossBattle",
            "mapSize": 34.0
          },
          "unitList": [
            {
              "unitID": 8390,
              "unitCount": 1,
              "unitLevel": 90
            }
          ],
          "subUnitList": [
            {
              "unitID": 8403,
              "unitCount": 1,
              "unitLevel": 45,
              "isHide": true
            },
            {
              "unitID": 8404,
              "unitCount": 1,
              "unitLevel": 45,
              "isHide": true
            },
            {
              "unitID": 8405,
              "unitCount": 1,
              "unitLevel": 45,
              "isHide": true
            },
            {
              "unitID": 8406,
              "unitCount": 1,
              "unitLevel": 45,
              "isHide": true
            },
            {
              "unitID": 8407,
              "unitCount": 1,
              "unitLevel": 45,
              "isHide": true
            },
            {
              "unitID": 8408,
              "unitCount": 1,
              "unitLevel": 45,
              "isHide": true
            },
            {
              "unitID": 8409,
              "unitCount": 1,
              "unitLevel": 45,
              "isHide": true
            },
            {
              "unitID": 8397,
              "unitCount": 1,
              "unitLevel": 45,
              "isHide": true
            },
            {
              "unitID": 8398,
              "unitCount": 1,
              "unitLevel": 60,
              "isHide": true
            },
            {
              "unitID": 8399,
              "unitCount": 1,
              "unitLevel": 45,
              "isHide": true
            },
            {
              "unitID": 8400,
              "unitCount": 1,
              "unitLevel": 60,
              "isHide": true
            },
            {
              "unitID": 8401,
              "unitCount": 1,
              "unitLevel": 45,
              "isHide": true
            },
            {
              "unitID": 8402,
              "unitCount": 1,
              "unitLevel": 63,
              "isHide": true
            },
            {
              "unitID": 8410,
              "unitCount": 1,
              "unitLevel": 90,
              "isHide": true
            },
            {
              "unitID": 8411,
              "unitCount": 1,
              "unitLevel": 45,
              "isHide": true
            },
            {
              "unitID": 8412,
              "unitCount": 1,
              "unitLevel": 45,
              "isHide": true
            },
            {
              "unitID": 8413,
              "unitCount": 1,
              "unitLevel": 45,
              "isHide": true
            }
          ],
          "bgmList": [
            "Battle_Cp7_Boss_4"
          ],
          "enemyPositionID": 104,
          "allyPositionID": 103
        }
      ],
      "staminaCost": 8,
      "recommendedLevel": 50,
      "turnLimit": 99,
      "questlist": [
        {
          "args": [
            "10"
          ],
          "localizeId": 1
        }
      ],
      "rewardList": [

      ],
      "story": {
        "enter": [
          
        ],
        "exit": [
          "7D112A"
        ],
        "others": [
          {
            "phase": "BEFORE_ROUND_END",
            "storyID": "7D112I",
            "storyIndex": 0
          },
          {
            "phase": "BEFORE_ROUND_END",
            "storyID": "7D112I2",
            "storyIndex": 1
          },
          {
            "phase": "BEFORE_ROUND_END",
            "storyID": "7D112I3",
            "storyIndex": 2
          },
          {
            "phase": "BEFORE_ROUND_END",
            "storyID": "7D112I4",
            "storyIndex": 3
          },
          {
            "phase": "BEFORE_ROUND_END",
            "storyID": "7D112I5",
            "storyIndex": 4
          }
        ]
      },
      "stageScriptList": [ "8390", "8410", "Chapter7SetAllyDefaultMpNotCustomizePosition" ],
      "includeBoss": 1
    },
    {
      "id": 10711,
      "isBatonPassOn": true,
      "stageLevel": 50,
      "stageType": "Abnormality",
      "participantInfo": {
        "min": 6,
        "max": 6
      },
      "waveList": [
        {
          "battleMapInfo": {
            "mapName": "LCorpElevator_v1"
          },
          "unitList": [
            {
              "unitID": 8161,
              "unitCount": 1,
              "unitLevel": 50
            }
          ],
          "bgmList": [
            "Battle_Cp1_Ally_1",
            "Battle_Cp1_Enemy_1"
          ]
        }
      ],
      "staminaCost": 0,
      "recommendedLevel": 50,
      "turnLimit": 99,
      "questlist": [
        {
          "args": [
            "10"
          ],
          "localizeId": 1
        }
      ],
      "rewardList": [],
      "stageScriptList": [
        "Chapter7SetAllyDefaultMp"
      ],
      "abstainSupporterCharacterIds": [ 3 ]
    },
    {
      "id": 10713,
      "isBatonPassOn": true,
      "stageLevel": 48,
      "stageType": "Abnormality",
      "participantInfo": {
        "min": 6,
        "max": 6
      },
      "waveList": [
        {
          "battleMapInfo": {
            "mapName": "Cp7_FathomsOfLamancha_1"
          },
          "unitList": [
            {
              "unitID": 8220,
              "unitCount": 1,
              "unitLevel": 48
            }
          ],
          "bgmList": [
            "Battle_Cp7_Enemy_5"
          ],
          "enemyPositionID": 13
        }
      ],
      "staminaCost": 0,
      "recommendedLevel": 48,
      "turnLimit": 99,
      "questlist": [
        {
          "args": [
            "10"
          ],
          "localizeId": 1
        }
      ],
      "rewardList": [],
      "stageScriptList": [
        "Chapter7SetAllyDefaultMp"
      ],
      "abstainSupporterCharacterIds": [ 3 ]
    }
  ]
}